[{"kind": "calendar#event", "etag": "\"3295042094236000\"", "id": "6bqunf8vopf44qbivqrem7gi3u_20220325T113000Z", "status": "confirmed", "htmlLink": "https://www.google.com/calendar/event?eid=NmJxdW5mOHZvcGY0NHFiaXZxcmVtN2dpM3VfMjAyMjAzMjVUMTEzMDAwWiBweWNvbi5rcl9rcXEyM2RtNTMzOW9oZTg3Z211YXZ0cW5yY0Bn&ctz=Asia/Seoul", "created": "2022-03-17T12:43:10.000Z", "updated": "2022-03-17T12:44:07.118Z", "summary": "\ud6c4\uc6d0\uc0ac \ud68c\uc758", "location": "https://us06web.zoom.us/j/85736634579?pwd=eU9MQm1ZYitJaTlaYlBzcGE3WldNQT09", "creator": {"email": "kst6294@pycon.kr"}, "organizer": {"email": "pycon.kr_kqq23dm5339ohe87gmuavtqnrc@group.calendar.google.com", "displayName": "PyCon Korea", "self": true}, "start": {"dateTime": "2022-03-25T20:30:00+09:00", "timeZone": "Asia/Seoul"}, "end": {"dateTime": "2022-03-25T22:30:00+09:00", "timeZone": "Asia/Seoul"}, "recurringEventId": "6bqunf8vopf44qbivqrem7gi3u", "originalStartTime": {"dateTime": "2022-03-25T20:30:00+09:00", "timeZone": "Asia/Seoul"}, "transparency": "transparent", "iCalUID": "6bqunf8vopf44qbivqrem7gi3u@google.com", "sequence": 2, "reminders": {"useDefault": true}, "eventType": "default"}, {"kind": "calendar#event", "etag": "\"3296078167446000\"", "id": "_64r34d9k84skcb9g8h2j4b9k6h336b9p64r32b9h8ksjeh236cskadi26k", "status": "confirmed", "htmlLink": "https://www.google.com/calendar/event?eid=XzY0cjM0ZDlrODRza2NiOWc4aDJqNGI5azZoMzM2YjlwNjRyMzJiOWg4a3NqZWgyMzZjc2thZGkyNmsgcHljb24ua3Jfa3FxMjNkbTUzMzlvaGU4N2dtdWF2dHFucmNAZw&ctz=Asia/Seoul", "created": "2022-03-23T12:38:03.000Z", "updated": "2022-03-23T12:38:03.723Z", "summary": "\ubaa8\uc5ec\uc11c \ud30c\uc900\uc704 \ub180\uae30", "creator": {"email": "syo@pycon.kr"}, "organizer": {"email": "pycon.kr_kqq23dm5339ohe87gmuavtqnrc@group.calendar.google.com", "displayName": "PyCon Korea", "self": true}, "start": {"dateTime": "2022-03-26T22:00:00+09:00", "timeZone": "Asia/Seoul"}, "end": {"dateTime": "2022-03-26T23:00:00+09:00", "timeZone": "Asia/Seoul"}, "iCalUID": "16254A9F-0DE2-44F3-9161-1E97DC39E6B5", "sequence": 0, "reminders": {"useDefault": true}, "eventType": "default"}]